djexception/__init__.py
djexception/asgi.py
djexception/settings.py
djexception/urls.py
djexception/wsgi.py
request_viewer/__init__.py
request_viewer/admin.py
request_viewer/apps.py
request_viewer/conf.py
request_viewer/middleware.py
request_viewer/models.py
request_viewer/tests.py
request_viewer/urls.py
request_viewer/utils.py
request_viewer/views.py
request_viewer/migrations/0001_initial.py
request_viewer/migrations/0002_exceptionmodel_alter_logger_id.py
request_viewer/migrations/__init__.py
request_viewer/templates/request_viewer/exception.html
request_viewer/templates/request_viewer/request.html
request_viewer/templates/request_viewer/fragments/filter.html
request_viewer/templates/request_viewer/fragments/modal.html
request_viewer/templates/request_viewer/fragments/pagination.html
request_viewer/templates/request_viewer/fragments/exception/modal.html
request_viewer/templates/request_viewer/fragments/exception/modal_content.html
request_viewer/templates/request_viewer/fragments/exception/table.html
request_viewer/templates/request_viewer/fragments/request/filter.html
request_viewer/templates/request_viewer/fragments/request/modal_content.html
request_viewer/templates/request_viewer/fragments/request/table.html
request_viewer/templatetags/__init__.py
request_viewer/templatetags/request_view_tag.py
django_request_viewer-1.0.3.dist-info/LICENSE
django_request_viewer-1.0.3.dist-info/METADATA
django_request_viewer-1.0.3.dist-info/WHEEL
django_request_viewer-1.0.3.dist-info/top_level.txt
django_request_viewer-1.0.3.dist-info/RECORD
