Metadata-Version: 2.1
Name: django-request-viewer
Version: 1.0.3
Summary: Log and view requests and exceptions made on your Django app
Home-page: https://github.com/sirrobot01/django-request-viewer
Author: Mukhtar Akere
Author-email: akeremukhtar10@gmail.com
License: BSD-3-Clause
Project-URL: Source, https://github.com/sirrobot01/django-request-viewer
Platform: UNKNOWN
Classifier: Environment :: Web Environment
Classifier: Framework :: Django
Classifier: Framework :: Django :: 3.1
Classifier: Intended Audience :: Developers
Classifier: License :: OSI Approved :: MIT License
Classifier: Operating System :: OS Independent
Classifier: Programming Language :: Python
Classifier: Programming Language :: Python :: 3
Classifier: Programming Language :: Python :: 3 :: Only
Classifier: Programming Language :: Python :: 3.6
Classifier: Programming Language :: Python :: 3.7
Classifier: Programming Language :: Python :: 3.8
Classifier: Topic :: Internet :: WWW/HTTP
Classifier: Topic :: Internet :: WWW/HTTP :: Dynamic Content
License-File: LICENSE
Requires-Dist: django (>=2.2)
